online_store161616/__init__.py
online_store161616/__main__.py
online_store161616/order_management.py
online_store161616/user_management.py
online_store161616-0.1.0.dist-info/METADATA
online_store161616-0.1.0.dist-info/WHEEL
online_store161616-0.1.0.dist-info/top_level.txt
online_store161616-0.1.0.dist-info/RECORD
